llmtune/__init__.py
llmtune/cli/__init__.py
llmtune/cli/toolkit.py
llmtune/config.yml
llmtune/constants/files.py
llmtune/data/__init__.py
llmtune/data/dataset_generator.py
llmtune/data/ingestor.py
llmtune/finetune/__init__.py
llmtune/finetune/generics.py
llmtune/finetune/lora.py
llmtune/inference/__init__.py
llmtune/inference/generics.py
llmtune/inference/lora.py
llmtune/pydantic_models/__init__.py
llmtune/pydantic_models/config_model.py
llmtune/qa/__init__.py
llmtune/qa/generics.py
llmtune/qa/qa_metrics.py
llmtune/qa/qa_tests.py
llmtune/ui/__init__.py
llmtune/ui/generics.py
llmtune/ui/rich_ui.py
llmtune/utils/__init__.py
llmtune/utils/ablation_utils.py
llmtune/utils/rich_print_utils.py
llmtune/utils/save_utils.py
llm_toolkit-0.2.3.dist-info/LICENSE
llm_toolkit-0.2.3.dist-info/METADATA
llm_toolkit-0.2.3.dist-info/WHEEL
llm_toolkit-0.2.3.dist-info/entry_points.txt
llm_toolkit-0.2.3.dist-info/RECORD
