Metadata-Version: 2.1
Name: llm-toolkit
Version: 0.2.3
Summary: LLM Finetuning resource hub + toolkit
Home-page: https://github.com/georgian-io/LLM-Finetuning-Toolkit
License: Apache 2.0
Keywords: llm,finetuning,language models,machine learning,deep learning
Author: Benjamin Ye
Author-email: benjamin.ye@georgian.io
Requires-Python: >=3.9,<=3.12
Classifier: Intended Audience :: Developers
Classifier: Intended Audience :: Science/Research
Classifier: License :: Other/Proprietary License
Classifier: Programming Language :: Python :: 3
Classifier: Programming Language :: Python :: 3.9
Classifier: Programming Language :: Python :: 3.10
Classifier: Programming Language :: Python :: 3.11
Classifier: Topic :: Scientific/Engineering :: Artificial Intelligence
Requires-Dist: absl-py (>=2.1.0,<3.0.0)
Requires-Dist: accelerate (>=0.27.0,<0.28.0)
Requires-Dist: ai21 (>=2.0.3,<3.0.0)
Requires-Dist: bitsandbytes (>=0.43.2)
Requires-Dist: datasets (>=2.17.0,<3.0.0)
Requires-Dist: einops (>=0.7.0,<0.8.0)
Requires-Dist: evaluate (>=0.4.1,<0.5.0)
Requires-Dist: ijson (>=3.2.3,<4.0.0)
Requires-Dist: ipdb (>=0.13.13,<0.14.0)
Requires-Dist: langchain (>=0.2.5,<0.3.0)
Requires-Dist: ninja (>=1.11.1.1,<2.0.0.0)
Requires-Dist: nltk (>=3.8.1,<4.0.0)
Requires-Dist: numpy (>=1.26.4,<2.0.0)
Requires-Dist: openai (>=1.12.0,<2.0.0)
Requires-Dist: packaging (>=23.2,<24.0)
Requires-Dist: pandas (>=2.2.0,<3.0.0)
Requires-Dist: peft (>=0.8.2,<0.9.0)
Requires-Dist: protobuf (>=4.25.2,<5.0.0)
Requires-Dist: py7zr (>=0.20.8,<0.21.0)
Requires-Dist: pydantic (>=2.6.1,<3.0.0)
Requires-Dist: pyyaml (>=6.0.1,<7.0.0)
Requires-Dist: rich (>=13.7.0,<14.0.0)
Requires-Dist: rouge-score (>=0.1.2,<0.2.0)
Requires-Dist: sentencepiece (>=0.1.99,<0.2.0)
Requires-Dist: shellingham (>=1.5.4,<2.0.0)
Requires-Dist: sqids (>=0.4.1,<0.5.0)
Requires-Dist: tiktoken (>=0.6.0,<0.7.0)
Requires-Dist: transformers (>=4.40.2,<4.41.0)
Requires-Dist: trl (>=0.8.6,<0.9.0)
Requires-Dist: typer (>=0.10.0,<0.11.0)
Requires-Dist: ujson (>=5.9.0,<6.0.0)
Requires-Dist: wandb (>=0.16.3,<0.17.0)
Project-URL: Repository, https://github.com/georgian-io/LLM-Finetuning-Toolkit
